open_clip/__init__.py
open_clip/bpe_simple_vocab_16e6.txt.gz
open_clip/coca_model.py
open_clip/constants.py
open_clip/convert.py
open_clip/factory.py
open_clip/hf_configs.py
open_clip/hf_model.py
open_clip/loss.py
open_clip/model.py
open_clip/model_configs/EVA01-g-14-plus.json
open_clip/model_configs/EVA01-g-14.json
open_clip/model_configs/EVA02-B-16.json
open_clip/model_configs/EVA02-E-14-plus.json
open_clip/model_configs/EVA02-E-14.json
open_clip/model_configs/EVA02-L-14-336.json
open_clip/model_configs/EVA02-L-14.json
open_clip/model_configs/MobileCLIP-B.json
open_clip/model_configs/MobileCLIP-S1.json
open_clip/model_configs/MobileCLIP-S2.json
open_clip/model_configs/PE-Core-B-16.json
open_clip/model_configs/PE-Core-L-14-336.json
open_clip/model_configs/PE-Core-S-16-384.json
open_clip/model_configs/PE-Core-T-16-384.json
open_clip/model_configs/PE-Core-bigG-14-448.json
open_clip/model_configs/RN101-quickgelu.json
open_clip/model_configs/RN101.json
open_clip/model_configs/RN50-quickgelu.json
open_clip/model_configs/RN50.json
open_clip/model_configs/RN50x16-quickgelu.json
open_clip/model_configs/RN50x16.json
open_clip/model_configs/RN50x4-quickgelu.json
open_clip/model_configs/RN50x4.json
open_clip/model_configs/RN50x64-quickgelu.json
open_clip/model_configs/RN50x64.json
open_clip/model_configs/ViT-B-16-SigLIP-256.json
open_clip/model_configs/ViT-B-16-SigLIP-384.json
open_clip/model_configs/ViT-B-16-SigLIP-512.json
open_clip/model_configs/ViT-B-16-SigLIP-i18n-256.json
open_clip/model_configs/ViT-B-16-SigLIP.json
open_clip/model_configs/ViT-B-16-SigLIP2-256.json
open_clip/model_configs/ViT-B-16-SigLIP2-384.json
open_clip/model_configs/ViT-B-16-SigLIP2-512.json
open_clip/model_configs/ViT-B-16-SigLIP2.json
open_clip/model_configs/ViT-B-16-plus-240.json
open_clip/model_configs/ViT-B-16-plus.json
open_clip/model_configs/ViT-B-16-quickgelu.json
open_clip/model_configs/ViT-B-16.json
open_clip/model_configs/ViT-B-32-256.json
open_clip_torch-3.0.0.dist-info/METADATA
open_clip_torch-3.0.0.dist-info/WHEEL
open_clip_torch-3.0.0.dist-info/entry_points.txt
open_clip_torch-3.0.0.dist-info/licenses/LICENSE
open_clip_torch-3.0.0.dist-info/RECORD
