Metadata-Version: 2.1
Name: open_clip_torch
Version: 3.0.0
Summary: Open reproduction of consastive language-image pretraining (CLIP) and related.
Keywords: pytorch,clip,image-text,language-image,multimodal
Author: Gabriel Ilharco, Mitchell Wortsman, Romain Beaumont
Author-Email: Ross Wightman <ross@huggingface.co>
License: MIT
Classifier: Development Status :: 4 - Beta
Classifier: Intended Audience :: Education
Classifier: Intended Audience :: Science/Research
Classifier: License :: OSI Approved :: MIT License
Classifier: Programming Language :: Python :: 3.9
Classifier: Programming Language :: Python :: 3.10
Classifier: Programming Language :: Python :: 3.11
Classifier: Programming Language :: Python :: 3.12
Classifier: Topic :: Scientific/Engineering
Classifier: Topic :: Scientific/Engineering :: Artificial Intelligence
Classifier: Topic :: Software Development
Classifier: Topic :: Software Development :: Libraries
Classifier: Topic :: Software Development :: Libraries :: Python Modules
Project-URL: homepage, https://github.com/mlfoundations/open_clip
Project-URL: repository, https://github.com/mlfoundations/open_clip
Requires-Python: >=3.9
Requires-Dist: torch>=2.0
Requires-Dist: torchvision
Requires-Dist: regex
Requires-Dist: ftfy
Requires-Dist: tqdm
Requires-Dist: huggingface-hub
Requires-Dist: safetensors
Requires-Dist: timm>=1.0.17
Provides-Extra: training
Requires-Dist: torch>=2.0; extra == "training"
Requires-Dist: webdataset<=0.2.86,>=0.2.5; extra == "training"
Requires-Dist: pandas; extra == "training"
Requires-Dist: transformers[sentencepiece]; extra == "training"
Requires-Dist: timm>=1.0.17; extra == "training"
Requires-Dist: fsspec; extra == "training"
Provides-Extra: test
Requires-Dist: pytest-split; extra == "test"
Requires-Dist: pytest; extra == "test"
Requires-Dist: open_clip_torch[training]; extra == "test"
